splight_toolbox/__init__.py
splight_toolbox/datasets/__init__.py
splight_toolbox/datasets/hydro.csv
splight_toolbox/datasets/sine_wave.csv
splight_toolbox/datasets/solar.csv
splight_toolbox/datasets/square_wave.csv
splight_toolbox/timeseries/__init__.py
splight_toolbox/timeseries/infinite_timeseries.py
splight_toolbox-0.0.9.dist-info/METADATA
splight_toolbox-0.0.9.dist-info/WHEEL
splight_toolbox-0.0.9.dist-info/top_level.txt
splight_toolbox-0.0.9.dist-info/RECORD
